Metadata-Version: 1.0
Name: mcgrep
Version: 0.1
Summary: Grep through memcached.
Home-page: http://github.com/storborg/mcgrep
Author: Scott Torborg
Author-email: storborg@mit.edu
License: GPL
Keywords: memcached memcache pylibmc diagnostics caching pentesting
Platform: UNKNOWN
Classifier: Development Status :: 3 - Alpha
Classifier: License :: OSI Approved :: GNU General Public License (GPL)
Classifier: Intended Audience :: Developers
Classifier: Natural Language :: English
Classifier: Programming Language :: Python
